[
  {
    "id": "1",
    "title": "Ep. 20, Ion Oboroceanu",
    "description": "In 2026, disruption and transformation will intensify, making job security uncertain. With AI and automation advancing fast, staying employable will require continuous adaptation and innovation.",
    "episodeNr": "Ep. 20",
    "audioUrl": "https://cdn.vunstaged.com/podcast/20.mp3",
    "topics": [
      "Job Market",
      "Hiring",
      "Company",
      "Culture",
      "PM",
      "Educational System",
      "AI"
    ]
  },
  {
    "id": "2",
    "title": "Welcome to the Podcast",
    "description": "We introduce the show, the hosts, and what to expect. We introduce the show, the hosts, and what to expect. asdasasdasdas asdasdasd",
    "episodeNr": "#2",
    "audioUrl": "",
    "topics": ["AI", "Hiring", "Architecture", "Technology", "Law"]
  },
  {
    "id": "3",
    "title": "Welcome to the Podcast",
    "description": "We introduce the show, the hosts, and what to expect. We introduce the show, the hosts, and what to expect. asdasasdasdas asdasdasd",
    "episodeNr": "#3",
    "audioUrl": "",
    "topics": ["AI", "Hiring", "Architecture", "Technology", "Law"]
  }
]
